h2o_wave_ml/__init__.py
h2o_wave_ml/config.py
h2o_wave_ml/dai.py
h2o_wave_ml/h2o3.py
h2o_wave_ml/ml.py
h2o_wave_ml/types.py
h2o_wave_ml/utils.py
h2o_wave_ml-0.8.1.dist-info/LICENSE
h2o_wave_ml-0.8.1.dist-info/METADATA
h2o_wave_ml-0.8.1.dist-info/WHEEL
h2o_wave_ml-0.8.1.dist-info/top_level.txt
h2o_wave_ml-0.8.1.dist-info/RECORD
