Metadata-Version: 2.1
Name: h2o-wave-ml
Version: 0.8.1
Summary: AutoML for Wave Apps
Home-page: https://github.com/h2oai/wave-ml
Author: H2O.ai
Author-email: support@h2o.ai
License: UNKNOWN
Platform: UNKNOWN
Classifier: Programming Language :: Python :: 3
Classifier: Programming Language :: Python :: 3.6
Classifier: Operating System :: POSIX :: Linux
Classifier: Intended Audience :: Developers
Classifier: License :: OSI Approved :: Apache Software License
Requires-Python: >=3.6.1
Requires-Dist: h2o
Requires-Dist: driverlessai
Requires-Dist: requests
